{"cameraMode":{"drawMode":0,"name":"Shaded","section":"Shading Mode"},"sceneLighting":true,"audioPlay":false,"sceneViewState":{"showFog":true,"showMaterialUpdate":false,"showSkybox":true,"showFlares":true,"showImageEffects":true,"showParticleSystems":true},"in2DMode":false,"pivot":{"x":14.583074569702149,"y":2.8897602558135988,"z":-7.276203632354736},"rotation":{"x":0.10828929394483566,"y":0.08371592313051224,"z":-0.00935116782784462,"w":0.9906296133995056},"size":-0.29115062952041628,"orthographic":false}